{   
    "items": 
        [
            "twop",
            "photometry",
            "histology",
            "videos",
            "ephys"
        ],
    "fp1":
        {
            "comment": "Source folder",
            "micename": "SZ",
            "twop": "\\\\nasquatch\\data\\2p\\stephen",
            "photometry": "\\\\anastasia\\data\\photometry",
            "histology": "\\\\anastasia\\data\\histology\\stephen",
            "videos": "\\\\anastasia\\data\\videos\\Stephen Z",
            "ephys": "\\\\anastasia\\data\\ephys\\stephen"
        },
    "fp2":
        {   "enable": true,
            "comment": "Target folder 1",
            "micename": "SZ",
            "twop": "R:\\Andermann_Lab_Archive\\active\\2photon\\stephen",
            "photometry": "R:\\Andermann_Lab_Archive\\active\\Photometry Experiments",
            "histology": "R:\\Andermann_Lab_Archive\\active\\histology\\stephen",
            "videos": "R:\\Andermann_Lab_Archive\\active\\videos\\stephen",
            "ephys": "R:\\Andermann_Lab_Archive\\active\\ephys\\stephen"
        },
    "fp3":
        {
            "enable": true,
            "comment": "Target folder 2",
            "micename": "SZ",            
            "twop": "R:\\SZ_p1\\2photon",
            "photometry": "R:\\SZ_p1\\Photometry Experiments",
            "histology": "R:\\SZ_p1\\histology",
            "videos": "R:\\SZ_p1\\videos",
            "ephys": "R:\\SZ_p1\\ephys"
        },
    "mousefolder": 
        [
            "SZ\\d*",
            "AL\\d*"
        ],
    "reportfp": "D:\\User Folders\\Stephen\\File matching\\stephen sync\\"
}